Metadata-Version: 2.1
Name: httpie-oauth1
Version: 1.2.2
Summary: OAuth 1.0a authentication plugin for HTTPie.
Home-page: https://github.com/qcif/httpie-oauth1
Download-URL: https://github.com/qcif/httpie-oauth1
Author: Hoylen Sue
Author-email: hoylen@hoylen.com
License: BSD
Project-URL: Bug Tracker, https://github.com/qcif/httpie-oauth1/issues
Platform: UNKNOWN
Classifier: Development Status :: 5 - Production/Stable
Classifier: Programming Language :: Python :: 3
Classifier: Environment :: Plugins
Classifier: License :: OSI Approved :: BSD License
Classifier: Topic :: Internet :: WWW/HTTP
Classifier: Topic :: Utilities
Requires-Python: >3.6.0
Provides-Extra: rsa
License-File: LICENSE
